panda_auth/__init__.py
panda_auth/create_key.py
panda_auth/get_key.py
panda_auth/hello.py
panda_auth/reset_hwid.py
panda_auth-0.3.dist-info/METADATA
panda_auth-0.3.dist-info/WHEEL
panda_auth-0.3.dist-info/top_level.txt
panda_auth-0.3.dist-info/RECORD
