Metadata-Version: 2.1
Name: panda-auth
Version: 0.3
Summary: Panda Auth key system official python module
Home-page: https://github.com/Sponsoparnordvpn/Panda_Auth
Author: Sponsoparnordvpn
Author-email: sponsoparnordvpn@gmail.com
Requires-Dist: requests
Requires-Dist: pyperclip
Requires-Dist: colorama
